contextcheck/__init__.py
contextcheck/assertions/__init__.py
contextcheck/assertions/assertions.py
contextcheck/assertions/factory.py
contextcheck/assertions/llm_eval_prompts.py
contextcheck/assertions/llm_metrics.py
contextcheck/assertions/settings.py
contextcheck/assertions/utils.py
contextcheck/connectors/__init__.py
contextcheck/connectors/connector.py
contextcheck/connectors/connector_echo.py
contextcheck/connectors/connector_http.py
contextcheck/connectors/connector_openai_compatible.py
contextcheck/endpoints/__init__.py
contextcheck/endpoints/endpoint.py
contextcheck/endpoints/endpoint_cc.py
contextcheck/endpoints/endpoint_config.py
contextcheck/endpoints/endpoint_dummy_echo.py
contextcheck/endpoints/endpoint_openai_compatible.py
contextcheck/endpoints/endpoint_tg_chatbot.py
contextcheck/endpoints/factory.py
contextcheck/executors/__init__.py
contextcheck/executors/executor.py
contextcheck/executors/tests_router.py
contextcheck/generators/__init__.py
contextcheck/generators/cc_api_wrapper.py
contextcheck/generators/endpoint_wrapper.py
contextcheck/generators/generate_answers.py
contextcheck/generators/generate_questions.py
contextcheck/generators/utils.py
contextcheck/interfaces/__init__.py
contextcheck/interfaces/interface.py
contextcheck/interfaces/interface_output_file.py
contextcheck/interfaces/interface_tui.py
contextcheck/loaders/__init__.py
contextcheck/loaders/yaml.py
contextcheck/models/__init__.py
contextcheck/models/models.py
contextcheck/models/request.py
contextcheck/models/response.py
contextcheck/question_answering.py
contextcheck/questions_generator.py
contextcheck/run_tests.py
ccheck-0.1.4.dist-info/entry_points.txt
ccheck-0.1.4.dist-info/LICENSE
ccheck-0.1.4.dist-info/METADATA
ccheck-0.1.4.dist-info/WHEEL
ccheck-0.1.4.dist-info/RECORD
