Metadata-Version: 2.1
Name: ccheck
Version: 0.1.4
Summary: A human-friendly framework for testing and evaluating LLMs, RAGs, and chatbots.
Home-page: https://github.com/Addepto/contextcheck
License: MIT
Keywords: LLM,RAG,Chatbot,Testing,Validation
Author: Addepto
Author-email: hi@addepto.com
Requires-Python: >=3.11,<4.0
Classifier: License :: OSI Approved :: MIT License
Classifier: Operating System :: OS Independent
Classifier: Programming Language :: Python :: 3
Classifier: Programming Language :: Python :: 3.11
Classifier: Programming Language :: Python :: 3.12
Classifier: Topic :: Software Development :: Testing
Provides-Extra: docs
Requires-Dist: fsspec (==2024.3.1)
Requires-Dist: gensim (>=4.3.3,<5.0.0)
Requires-Dist: jinja2 (>=3.1.4,<4.0.0)
Requires-Dist: jsonschema (>=4.23.0,<5.0.0)
Requires-Dist: langchain_community (>=0.3.1,<0.4.0)
Requires-Dist: loguru (>=0.7.2,<0.8.0)
Requires-Dist: mike (>=2.0.0,<3.0.0) ; extra == "docs"
Requires-Dist: mkdocs (>=1.5.3,<2.0.0) ; extra == "docs"
Requires-Dist: mkdocstrings (>=0.24.0,<0.25.0) ; extra == "docs"
Requires-Dist: mkdocstrings-python (>=1.8.0,<2.0.0) ; extra == "docs"
Requires-Dist: nltk (>=3.8.1,<4.0.0)
Requires-Dist: openai (>=1.30.1,<2.0.0)
Requires-Dist: pydantic (>=2.7.1,<3.0.0)
Requires-Dist: python-dotenv (>=1.0.1,<2.0.0)
Requires-Dist: pyyaml (>=6.0.1,<7.0.0)
Requires-Dist: requests (>=2.31.0,<3.0.0)
Requires-Dist: rich (>=13.7.1,<14.0.0)
Project-URL: Repository, https://github.com/Addepto/contextcheck
